fastpat/__init__.py
fastpat/__main__.py
fastpat/cli.py
fastpat/firms/assign.py
fastpat/firms/cites.py
fastpat/firms/cluster.py
fastpat/firms/merge.py
fastpat/meta/apply_files.txt
fastpat/meta/assign_files.txt
fastpat/meta/grant_files.txt
fastpat/meta/maint_files.txt
fastpat/meta/tmapply_files.txt
fastpat/parse/apply.py
fastpat/parse/assign.py
fastpat/parse/compustat.py
fastpat/parse/grant.py
fastpat/parse/maint.py
fastpat/parse/tmapply.py
fastpat/tools/concat.py
fastpat/tools/fetch.py
fastpat/tools/parse.py
fastpat/tools/simcore.pyx
fastpat/tools/simhash.py
fastpat/tools/standardize.py
fastpat/tools/tables.py
fastpat-0.9.2.dist-info/LICENSE
fastpat-0.9.2.dist-info/METADATA
fastpat-0.9.2.dist-info/WHEEL
fastpat-0.9.2.dist-info/entry_points.txt
fastpat-0.9.2.dist-info/top_level.txt
fastpat-0.9.2.dist-info/RECORD
