Metadata-Version: 2.1
Name: fastpat
Version: 0.9.2
Summary: USPTO patent data fetcher and parser
Author-email: Doug Hanley <thesecretaryofwar@gmail.com>
License: MIT
Project-URL: Homepage, http://github.com/iamlemec/fastpat
Keywords: patents,clustering,economics
Classifier: License :: OSI Approved :: MIT License
Classifier: Programming Language :: Python
Classifier: Programming Language :: Python :: 3
Requires-Python: >=3.7
License-File: LICENSE
Requires-Dist: fire
Requires-Dist: numpy
Requires-Dist: pandas
Requires-Dist: lxml
Requires-Dist: xxhash
Requires-Dist: editdistance
Requires-Dist: networkx
Requires-Dist: Cython
